{
    "strategic_recommendation": {
        "target_region": "Region 0 ((7670) Funcheir)",
        "opportunity_score": 53.62,
        "market_gap": "High frustration index identified in cluster."
    },
    "full_score_map": {
        "338554": 53.62,
        "275662": 53.62,
        "177225": 53.62,
        "476938": 53.62,
        "646606": 53.62,
        "109040": 53.62,
        "434834": 53.62,
        "372698": 53.62,
        "163064": 53.62,
        "588564": 53.62,
        "73881": 53.62,
        "13808": 53.62,
        "461743": 53.62,
        "92831": 53.62,
        "29073": 53.62,
        "556333": 53.62,
        "119482": 53.62,
        "304594": 53.62,
        "440341": 53.62,
        "361330": 53.62,
        "13843": 53.62,
        "192419": 53.62,
        "161746": 53.62,
        "463241": 53.62,
        "556029": 53.62,
        "299555": 53.62,
        "475330": 53.62,
        "389406": 53.62,
        "418320": 53.62,
        "50070": 53.62,
        "35905": 53.62,
        "477612": 53.62,
        "317227": 53.62,
        "33492": 53.62,
        "474342": 53.62,
        "69788": 53.62,
        "589090": 53.62,
        "25558": 53.62,
        "85517": 53.62,
        "96065": 53.62,
        "310872": 53.62,
        "105888": 53.62,
        "496539": 53.62,
        "185459": 53.62,
        "381425": 53.62,
        "587424": 53.62,
        "396566": 53.62,
        "341235": 53.62,
        "223493": 53.62,
        "162119": 53.62,
        "45946": 53.62,
        "110836": 53.62,
        "8637": 53.62,
        "18105": 53.62,
        "153566": 53.62,
        "187368": 53.62,
        "442109": 53.62,
        "86930": 53.62,
        "153560": 53.62,
        "107576": 53.62,
        "46360": 53.62,
        "311902": 53.62,
        "482151": 53.62,
        "118590": 53.62,
        "370099": 53.62,
        "314760": 53.62,
        "19694": 53.62,
        "553945": 53.62,
        "130521": 53.62,
        "485274": 53.62,
        "420351": 53.62,
        "428897": 53.62,
        "89145": 53.62,
        "97590": 53.62,
        "46411": 53.62,
        "111308": 53.62,
        "398761": 53.62,
        "20450": 53.62,
        "35314": 53.62,
        "311320": 53.62,
        "47885": 53.62,
        "40034": 53.62,
        "101861": 53.62,
        "99805": 53.62,
        "157181": 53.62,
        "18333": 53.62,
        "24042": 53.62,
        "364858": 53.62,
        "46361": 53.62,
        "361231": 53.62,
        "303940": 53.62,
        "177331": 53.62,
        "246912": 53.62,
        "260875": 53.62,
        "222022": 53.62,
        "420555": 53.62,
        "122829": 53.62,
        "242334": 53.62,
        "113547": 53.62,
        "341152": 53.62,
        "165654": 53.62,
        "211999": 53.62,
        "114103": 53.62,
        "580214": 53.62,
        "113748": 53.62,
        "335819": 53.62,
        "169931": 53.62,
        "412703": 53.62,
        "114096": 53.62,
        "439205": 53.62,
        "23784": 53.62,
        "414156": 53.62,
        "53648": 53.62,
        "30087": 53.62,
        "212659": 53.62,
        "26016": 53.62
    },
    "clusters": [
        {
            "cluster_name": "Region 0 ((7670) Funcheir)",
            "opportunity_score": 53.62,
            "top_performing_p4n_ids": [
                8637,
                177331,
                18333
            ]
        }
    ]
}